makejxl/__init__.py
makejxl-0.1.5.dist-info/LICENSE
makejxl-0.1.5.dist-info/METADATA
makejxl-0.1.5.dist-info/WHEEL
makejxl-0.1.5.dist-info/entry_points.txt
makejxl-0.1.5.dist-info/top_level.txt
makejxl-0.1.5.dist-info/RECORD
