Metadata-Version: 2.1
Name: makejxl
Version: 0.1.5
Summary: This tool will bulk encode image files in given directory to JPEG-XL
Home-page: https://github.com/varnav/makejxl
Author: Evgeny Varnavskiy
Author-email: varnavruz@gmail.com
License: UNKNOWN
Keywords: jpeg,jpeg-xl,transcoder
Platform: UNKNOWN
Classifier: Development Status :: 4 - Beta
Classifier: Environment :: MacOS X
Classifier: Environment :: Win32 (MS Windows)
Classifier: Intended Audience :: End Users/Desktop
Classifier: License :: OSI Approved :: MIT License
Classifier: Operating System :: OS Independent
Classifier: Topic :: Scientific/Engineering :: Image Processing
Classifier: Topic :: Utilities
Classifier: Topic :: Multimedia :: Graphics
Classifier: Environment :: Console
Classifier: Programming Language :: Python :: 3.9
Classifier: Programming Language :: Python :: 3 :: Only
Requires-Python: >=3.7
Requires-Dist: click (>=7.1.2)
